pdfrw/__init__.py
pdfrw/buildxobj.py
pdfrw/compress.py
pdfrw/crypt.py
pdfrw/errors.py
pdfrw/findobjs.py
pdfrw/pagemerge.py
pdfrw/pdfreader.py
pdfrw/pdfwriter.py
pdfrw/py23_diffs.py
pdfrw/tokens.py
pdfrw/toreportlab.py
pdfrw/uncompress.py
pdfrw/objects/__init__.py
pdfrw/objects/pdfarray.py
pdfrw/objects/pdfdict.py
pdfrw/objects/pdfindirect.py
pdfrw/objects/pdfname.py
pdfrw/objects/pdfobject.py
pdfrw/objects/pdfstring.py
pdfrw2-0.5.0.dist-info/LICENSE.txt
pdfrw2-0.5.0.dist-info/METADATA
pdfrw2-0.5.0.dist-info/WHEEL
pdfrw2-0.5.0.dist-info/top_level.txt
pdfrw2-0.5.0.dist-info/zip-safe
pdfrw2-0.5.0.dist-info/RECORD
