Metadata-Version: 2.1
Name: pdfrw2
Version: 0.5.0
Summary: PDF file reader/writer library
Home-page: https://github.com/sarnold/pdfrw
Author: Patrick Maupin
Author-email: pmaupin@gmail.com
License: MIT
Keywords: pdf vector graphics PDF nup watermark split join merge
Platform: Independent
Classifier: Development Status :: 4 - Beta
Classifier: Intended Audience :: Developers
Classifier: License :: OSI Approved :: MIT License
Classifier: Operating System :: OS Independent
Classifier: Programming Language :: Python
Classifier: Programming Language :: Python :: 3
Classifier: Programming Language :: Python :: 3.6
Classifier: Programming Language :: Python :: 3.7
Classifier: Programming Language :: Python :: 3.8
Classifier: Programming Language :: Python :: 3.9
Classifier: Topic :: Multimedia :: Graphics :: Graphics Conversion
Classifier: Topic :: Software Development :: Libraries
Classifier: Topic :: Text Processing
Classifier: Topic :: Printing
Classifier: Topic :: Utilities
